hearpreprocess/__init__.py
hearpreprocess/audio_dir_stats.py
hearpreprocess/dcase2016_task2.py
hearpreprocess/nsynth_pitch.py
hearpreprocess/nsynth_pitch_kfold.py
hearpreprocess/pipeline.py
hearpreprocess/runner.py
hearpreprocess/sampler.py
hearpreprocess/speech_commands.py
hearpreprocess/spoken_digit.py
hearpreprocess/tfds_pipeline.py
hearpreprocess/tfds_speech_commands.py
hearpreprocess/secrettasks/__init__.py
hearpreprocess/secrettasks/hearsecrettasks/__init__.py
hearpreprocess/secrettasks/hearsecrettasks/beehive_states_fold0.py
hearpreprocess/secrettasks/hearsecrettasks/beehive_states_fold1.py
hearpreprocess/secrettasks/hearsecrettasks/beijing_opera.py
hearpreprocess/secrettasks/hearsecrettasks/coughvid.py
hearpreprocess/secrettasks/hearsecrettasks/esc50.py
hearpreprocess/secrettasks/hearsecrettasks/fsd50k.py
hearpreprocess/secrettasks/hearsecrettasks/gunshot_triangulation.py
hearpreprocess/secrettasks/hearsecrettasks/libricount.py
hearpreprocess/secrettasks/hearsecrettasks/maestro.py
hearpreprocess/secrettasks/hearsecrettasks/mridangam_stroke.py
hearpreprocess/secrettasks/hearsecrettasks/mridangam_tonic.py
hearpreprocess/secrettasks/hearsecrettasks/tfds_crema_d.py
hearpreprocess/secrettasks/hearsecrettasks/tfds_gtzan.py
hearpreprocess/secrettasks/hearsecrettasks/tfds_gtzan_music_speech.py
hearpreprocess/secrettasks/hearsecrettasks/vocal_imitation.py
hearpreprocess/secrettasks/hearsecrettasks/vox_lingua_top10.py
hearpreprocess/util/__init__.py
hearpreprocess/util/audio.py
hearpreprocess/util/luigi.py
hearpreprocess/util/task_config.py
hearpreprocess-2021.1.1.dist-info/LICENSE
hearpreprocess-2021.1.1.dist-info/METADATA
hearpreprocess-2021.1.1.dist-info/WHEEL
hearpreprocess-2021.1.1.dist-info/top_level.txt
hearpreprocess-2021.1.1.dist-info/RECORD
