Metadata-Version: 2.1
Name: hearpreprocess
Version: 2021.1.1
Summary: Holistic Evaluation of Audio Representations (HEAR) 2021 -- Preprocessing Pipeline
Home-page: https://github.com/hearbenchmark/hear-preprocess
Download-URL: https://github.com/hearbenchmark/hear-preprocess
Author: 
Author-email: 
License: Apache-2.0
Project-URL: Bug Tracker, https://github.com/hearbenchmark/hear-preprocess/issues
Project-URL: Source Code, https://github.com/hearbenchmark/hear-preprocess
Requires-Python: >=3.7
License-File: LICENSE
Requires-Dist: click
Requires-Dist: luigi
Requires-Dist: numpy (==1.19.2)
Requires-Dist: numba (==0.48)
Requires-Dist: pandas
Requires-Dist: python-slugify
Requires-Dist: requests
Requires-Dist: soundfile
Requires-Dist: spotty
Requires-Dist: tensorflow-datasets
Requires-Dist: tqdm
Requires-Dist: scikit-learn (>=0.24.2)
Requires-Dist: ffmpeg-python
Requires-Dist: note-seq
Requires-Dist: tensorflow (>=2.0)
Requires-Dist: schema
Requires-Dist: patool
Provides-Extra: dev
Requires-Dist: pre-commit ; extra == 'dev'
Requires-Dist: black ; extra == 'dev'
Requires-Dist: pytest ; extra == 'dev'
Requires-Dist: pytest-cov ; extra == 'dev'
Requires-Dist: pytest-env ; extra == 'dev'
Provides-Extra: test
Requires-Dist: pytest ; extra == 'test'
Requires-Dist: pytest-cov ; extra == 'test'
Requires-Dist: pytest-env ; extra == 'test'
